rocket/__init__.py
rocket/rocket.py
mazapackagehaha-1.0.0.dist-info/METADATA
mazapackagehaha-1.0.0.dist-info/WHEEL
mazapackagehaha-1.0.0.dist-info/top_level.txt
mazapackagehaha-1.0.0.dist-info/RECORD
