Metadata-Version: 2.4
Name: mazapackagehaha
Version: 1.0.0
Summary: An awesome package that does something
Home-page: https://pypi.org/project/mazapackagehaha/
Author: Amine Mazari
Author-email: lacosteamine128@gmail.com
Dynamic: author
Dynamic: author-email
Dynamic: description
Dynamic: description-content-type
Dynamic: home-page
Dynamic: summary
